{"lastUsed":1606980363932,"path":"C:\/Users\/punch\/Documents\/GitHub\/High-School-Computer-Science-Files\/CS3\/LinkedLists","projectCount":7,"recentFiles":[{"path":"\/Traveling Salesperson 2.0\/src","parentWorkspace":"C:\/Users\/punch\/Documents\/GitHub\/High-School-Computer-Science-Files\/CS3\/LinkedLists","name":"TSPTimer.java","lastModified":1606980049105,"locationURI":"file:\/C:\/Users\/punch\/Documents\/GitHub\/High-School-Computer-Science-Files\/CS3\/LinkedLists\/Traveling%20Salesperson%202.0\/src\/TSPTimer.java"}]}